rcs_pydantic/__init__.py
rcs_pydantic/enums.py
rcs_pydantic/errors.py
rcs_pydantic/exceptions.py
rcs_pydantic/main.py
rcs_pydantic/scheme.py
rcs_pydantic-2.0.0.dist-info/LICENSE
rcs_pydantic-2.0.0.dist-info/METADATA
rcs_pydantic-2.0.0.dist-info/WHEEL
rcs_pydantic-2.0.0.dist-info/RECORD
