Metadata-Version: 2.1
Name: rcs-pydantic
Version: 2.0.0
Summary: 
Home-page: https://github.com/xncbf/rcs-pydantic
License: MIT
Keywords: pydantic,rcs,fastapi
Author: xncbf
Author-email: xncbf12@gmail.com
Requires-Python: >=3.8,<4.0
Classifier: License :: OSI Approved :: MIT License
Classifier: Programming Language :: Python :: 3
Classifier: Programming Language :: Python :: 3.8
Classifier: Programming Language :: Python :: 3.9
Classifier: Programming Language :: Python :: 3.10
Classifier: Programming Language :: Python :: 3.11
Classifier: Programming Language :: Python :: 3.12
Requires-Dist: pydantic (>=2.0.0,<3.0.0)
Project-URL: Repository, https://github.com/xncbf/rcs-pydantic
